wagtailapi_legacy/__init__.py
wagtailapi_legacy/v1/__init__.py
wagtailapi_legacy/v1/apps.py
wagtailapi_legacy/v1/endpoints.py
wagtailapi_legacy/v1/filters.py
wagtailapi_legacy/v1/pagination.py
wagtailapi_legacy/v1/router.py
wagtailapi_legacy/v1/serializers.py
wagtailapi_legacy/v1/signal_handlers.py
wagtailapi_legacy/v1/urls.py
wagtailapi_legacy/v1/utils.py
wagtailapi_legacy/v1/tests/__init__.py
wagtailapi_legacy/v1/tests/test_documents.py
wagtailapi_legacy/v1/tests/test_images.py
wagtailapi_legacy/v1/tests/test_pages.py
wagtailapi_legacy-1.0.1.dist-info/METADATA
wagtailapi_legacy-1.0.1.dist-info/RECORD
wagtailapi_legacy-1.0.1.dist-info/WHEEL
wagtailapi_legacy-1.0.1.dist-info/top_level.txt
