Metadata-Version: 2.1
Name: wagtailapi-legacy
Version: 1.0.1
Summary: UNKNOWN
Home-page: UNKNOWN
Author: Karl Hobley
Author-email: karl@kaed.uk
License: BSD
Platform: UNKNOWN
Classifier: Development Status :: 5 - Production/Stable
Classifier: Environment :: Web Environment
Classifier: Intended Audience :: Developers
Classifier: License :: OSI Approved :: BSD License
Classifier: Operating System :: OS Independent
Classifier: Programming Language :: Python
Classifier: Programming Language :: Python :: 3
Classifier: Programming Language :: Python :: 3.4
Classifier: Programming Language :: Python :: 3.5
Classifier: Programming Language :: Python :: 3.6
Classifier: Framework :: Django
Classifier: Framework :: Django :: 1.11
Classifier: Framework :: Django :: 2.0
Classifier: Topic :: Internet :: WWW/HTTP :: Site Management
Provides-Extra: testing
Requires-Dist: six (>=1.10.0)
Provides-Extra: testing
Requires-Dist: Django (==2.0.5); extra == 'testing'
Requires-Dist: wagtail (==2.0.1); extra == 'testing'
Requires-Dist: mock (<2,>=1); extra == 'testing'
